pegasus/ImageBind/.assets/bird_audio.wav
pegasus/ImageBind/.assets/bird_image.jpg
pegasus/ImageBind/.assets/car_audio.wav
pegasus/ImageBind/.assets/car_image.jpg
pegasus/ImageBind/.assets/dog_audio.wav
pegasus/ImageBind/.assets/dog_image.jpg
pegasus/ImageBind/.gitignore
pegasus/ImageBind/CODE_OF_CONDUCT.md
pegasus/ImageBind/CONTRIBUTING.md
pegasus/ImageBind/LICENSE
pegasus/ImageBind/README.md
pegasus/ImageBind/__init__.py
pegasus/ImageBind/bpe_simple_vocab_16e6.txt.gz
pegasus/ImageBind/data.py
pegasus/ImageBind/model_card.md
pegasus/ImageBind/models/__init__.py
pegasus/ImageBind/models/helpers.py
pegasus/ImageBind/models/imagebind_model.py
pegasus/ImageBind/models/multimodal_preprocessors.py
pegasus/ImageBind/models/transformer.py
pegasus/ImageBind/requirements.txt
pegasus/__init__.py
pegasus/embedding_functions.py
pegasus/errors.py
pegasus/main.py
pegasus/types.py
pegasusx-0.4.0.dist-info/LICENSE
pegasusx-0.4.0.dist-info/WHEEL
pegasusx-0.4.0.dist-info/METADATA
pegasusx-0.4.0.dist-info/RECORD
