Metadata-Version: 2.1
Name: pegasusx
Version: 0.4.0
Summary: pegasus - Pytorch
Home-page: https://github.com/kyegomez/pegasus
License: MIT
Keywords: artificial intelligence,deep learning,optimizers,Prompt Engineering
Author: Kye Gomez
Author-email: kye@apac.ai
Requires-Python: >=3.6,<4.0
Classifier: Development Status :: 4 - Beta
Classifier: Intended Audience :: Developers
Classifier: License :: OSI Approved :: MIT License
Classifier: Programming Language :: Python :: 3
Classifier: Programming Language :: Python :: 3.6
Classifier: Programming Language :: Python :: 3.7
Classifier: Programming Language :: Python :: 3.8
Classifier: Programming Language :: Python :: 3.9
Classifier: Programming Language :: Python :: 3.10
Classifier: Programming Language :: Python :: 3.11
Classifier: Programming Language :: Python :: 3.6
Classifier: Topic :: Scientific/Engineering :: Artificial Intelligence
Requires-Dist: decord (==0.6.0)
Requires-Dist: einops
Requires-Dist: ftfy
Requires-Dist: fvcore
Requires-Dist: hnswlib (==0.7.0)
Requires-Dist: joblib
Requires-Dist: numba
Requires-Dist: pandas (==1.3.5)
Requires-Dist: pydantic (==1.9.0)
Requires-Dist: pytorchvideo
Requires-Dist: regex
Requires-Dist: requests (==2.28.1)
Requires-Dist: timm (==0.6.7)
Requires-Dist: torch
Requires-Dist: torchaudio
Requires-Dist: torchvision
Requires-Dist: typing_extensions (==4.5.0)
Requires-Dist: uvicorn[standard] (==0.18.3)
Project-URL: Repository, https://github.com/kyegomez/pegasus
